libname/COINFLIPPY.py
libname/__init__.py
COIN_FLIPPY-0.0.1.dist-info/METADATA
COIN_FLIPPY-0.0.1.dist-info/WHEEL
COIN_FLIPPY-0.0.1.dist-info/top_level.txt
COIN_FLIPPY-0.0.1.dist-info/RECORD
